sigsleep/__init__.py
sigsleep/_version.py
sigsleep/py.typed
sigsleep/sigsleep.py
sigsleep-2.0.1.dist-info/LICENSE
sigsleep-2.0.1.dist-info/METADATA
sigsleep-2.0.1.dist-info/WHEEL
sigsleep-2.0.1.dist-info/entry_points.txt
sigsleep-2.0.1.dist-info/top_level.txt
sigsleep-2.0.1.dist-info/RECORD
