Metadata-Version: 2.1
Name: sigsleep
Version: 2.0.1
Summary: Sleep that prints info upon receiving a specified signal
License: GPL
Project-URL: Homepage, https://github.com/zwimer/sigsleep
Classifier: Programming Language :: Python :: 3
Classifier: Programming Language :: Python :: 3.8
Requires-Python: >=3.8
License-File: LICENSE
